mozaggregator/__init__.py
mozaggregator/aggregator.py
mozaggregator/config.py
mozaggregator/constants.py
mozaggregator/db.py
mozaggregator/scalar.py
mozaggregator/service.py
mozaggregator/sql.py
mozaggregator/temp.py
python_mozaggregator-0.3.0.2.dist-info/DESCRIPTION.rst
python_mozaggregator-0.3.0.2.dist-info/METADATA
python_mozaggregator-0.3.0.2.dist-info/RECORD
python_mozaggregator-0.3.0.2.dist-info/WHEEL
python_mozaggregator-0.3.0.2.dist-info/metadata.json
python_mozaggregator-0.3.0.2.dist-info/top_level.txt
